Metadata-Version: 2.1
Name: pywx
Version: 0.0.0
Summary: thread-safe python object pool
Home-page: https://github.com/btmorex/pywx
Author: Avery Fay
Author-email: avery@shadypixel.com
License: MIT
Platform: UNKNOWN
